guillotina_nuclia/__init__.py
guillotina_nuclia/api.py
guillotina_nuclia/install.py
guillotina_nuclia/permissions.py
guillotina_nuclia/utility.py
guillotina_nuclia/content/__init__.py
guillotina_nuclia/content/chat.py
guillotina_nuclia/interfaces/__init__.py
guillotina_nuclia/interfaces/chat.py
guillotina_nuclia-1.0.7.dist-info/licenses/LICENSE
guillotina_nuclia-1.0.7.dist-info/METADATA
guillotina_nuclia-1.0.7.dist-info/WHEEL
guillotina_nuclia-1.0.7.dist-info/top_level.txt
guillotina_nuclia-1.0.7.dist-info/zip-safe
guillotina_nuclia-1.0.7.dist-info/RECORD
