Metadata-Version: 2.4
Name: guillotina_nuclia
Version: 1.0.7
Summary: nuclia support for guillotina
Home-page: https://github.com/guillotinaweb/guillotina_nuclia
Author: Nil Bacardit Vinyals
Author-email: n.bacardit@iskra.cat
License: GPL version 3
Keywords: AI async guillotina nuclia
Classifier: Programming Language :: Python :: 3.8
Classifier: Programming Language :: Python :: 3.9
Classifier: Programming Language :: Python :: 3.10
Classifier: Programming Language :: Python :: 3.11
Classifier: Topic :: Software Development :: Libraries :: Python Modules
License-File: LICENSE
Requires-Dist: guillotina>=7.0.0
Requires-Dist: nuclia>=4.9.11
Provides-Extra: test
Requires-Dist: async_asgi_testclient; extra == "test"
Requires-Dist: pytest>=5.0; extra == "test"
Requires-Dist: pytest-asyncio==0.18.3; extra == "test"
Requires-Dist: coverage; extra == "test"
Requires-Dist: pytest-cov; extra == "test"
Requires-Dist: pytest-docker-fixtures[pg]>=1.3.0; extra == "test"
Requires-Dist: docker; extra == "test"
Requires-Dist: aiohttp<4.0.0,>=3.0.0; extra == "test"
Dynamic: author
Dynamic: author-email
Dynamic: classifier
Dynamic: description
Dynamic: home-page
Dynamic: keywords
Dynamic: license
Dynamic: license-file
Dynamic: provides-extra
Dynamic: requires-dist
Dynamic: summary
